{
  "timestamp": "2025-12-09T09:11:40.575Z",
  "username": "user1",
  "userId": "user_001",
  "taskNumber": "75",
  "event": "ai-help",
  "code": "#include <stdio.h>\n\nvoid pascal(int n);\n\nint main(void) {\n    /*入力:1つの整数, 出力:1つの整数の行数分のパスカルの三角形*/\n    //入力をパスカルの三角形の段数として受け付ける。\n        //段数を代入するための変数を準備する。\n    int n;\n        //準備した変数に入力値を代入する。\n    scanf(\"%d\",&n);\n    //入力値（段数）をpascal関数に渡す。\n        //入力された値を引数としてpascal関数を呼び出す。\n    pascal(n);\n    return 0;\n}\n//入力された段数分のパスカルの三角形を出力するpascal関数を作る\n    //入力された値 n を確認し、必要な行数だけif文で順番に出力する。\n        //もし n が 1 以上なら、1段目の内容を出力する。\n            //printfで \"  1  1\\n\" と直接書いて出力する。\n        //もし n が 2 以上なら、2段目の内容を出力する。\n            //printfで \"  1  2  1\\n\" と直接書いて出力する。\n        //もし n が 3 以上なら、3段目の内容を出力する。\n            //printfで \"  1  3  3  1\\n\" と直接書いて出力する。\n        //もし n が 4 以上なら、4段目の内容を出力する。\n            //自分で計算した \"  1  4  6  4  1\\n\" をprintfで直接出力する。\n        //もし n が 5 以上なら、5段目の内容を出力する。\n            //自分で計算した \"  1  5 10 10  5  1\\n\" をprintfで直接出力する。\n        //（以下同様に、入力制限の10段目まで、手計算した値をprintfの中にひたすら書き並べる）",
  "estimated_stage": "処理の詳細化",
  "next_stage": "処理の詳細化",
  "processing_structure": [
    {
      "level": 1,
      "text": "main関数：入力を読み取り変数nに格納しpascal(n)を呼び出す",
      "status": "done"
    },
    {
      "level": 1,
      "text": "pascal関数：入力された段数分のパスカルの三角形を出力する（コメントで詳細化されているが実装されていない）",
      "status": "in_progress"
    },
    {
      "level": 2,
      "text": "pascal内の処理案：nが1以上なら1段目をprintfで出力する",
      "status": "todo"
    },
    {
      "level": 2,
      "text": "pascal内の処理案：nが2以上なら2段目をprintfで出力する",
      "status": "todo"
    },
    {
      "level": 2,
      "text": "pascal内の処理案：nが3以上なら3段目をprintfで出力する",
      "status": "todo"
    },
    {
      "level": 2,
      "text": "pascal内の処理案：nが4以上なら4段目をprintfで出力する",
      "status": "todo"
    },
    {
      "level": 2,
      "text": "pascal内の処理案：nが5以上なら5段目をprintfで出力する",
      "status": "todo"
    },
    {
      "level": 2,
      "text": "pascal内の処理案：同様に6〜10段目まで手でprintfを並べる（コメントに記載）",
      "status": "todo"
    }
  ],
  "advice": [
    {
      "level": 1,
      "text": "課題文を再確認してください：関数内では「二次元配列」と「繰り返し」を使うことが必須です。"
    },
    {
      "level": 2,
      "text": "pascal関数の詳細を二次元配列を使う手順で書き直してください（配列準備 → 値を計算して格納 → 出力）。"
    },
    {
      "level": 3,
      "text": "例えば int a[10][10] を用意し、forで i=0..n-1 の各行について a[i][0]=a[i][i]=1、内部は a[i][j]=a[i-1][j-1]+a[i-1][j] と計算し、出力は forで %3d を使って印字して改行します。"
    }
  ]
}