{
  "timestamp": "2025-12-17T09:17:16.803Z",
  "username": "user01",
  "userId": "user_001",
  "taskNumber": "49",
  "event": "ai-help",
  "code": "#include <stdio.h>\n\nint main(void) {\n    /*入力:1つの整数, \n    出力:1行目に'*'、2行目に'**'…n行目に'*'をn個、最後に 'COUNT=' と合計*/\n    // 1. 入力を受け取る\n    // 2. tri3を呼ぶ\n    // 3. COUNTは n*(n+1)/2 で計算して表示\n    return 0;\n}",
  "estimated_stage": "処理の大枠決定",
  "next_stage": "処理の詳細化",
  "processing_structure": [
    {
      "level": 1,
      "text": "main関数：入力を受け取り、tri3を呼び、COUNTを表示する全体の流れ",
      "status": "in_progress"
    },
    {
      "level": 2,
      "text": "入力を受け取る（1つの整数 n を scanf で読む）",
      "status": "in_progress"
    },
    {
      "level": 2,
      "text": "tri3 を呼ぶ（再帰で三角形を出力する関数を使うことを計画）",
      "status": "in_progress"
    },
    {
      "level": 2,
      "text": "COUNT を n*(n+1)/2 で計算して出力する（コメントで示されている）",
      "status": "in_progress"
    },
    {
      "level": 1,
      "text": "tri3 関数（別関数として作ることが要件にあるが未実装）",
      "status": "todo"
    },
    {
      "level": 2,
      "text": "line3 関数（1行分の'*'を出力し、出力時にカウンタを増やす再帰関数・未実装）",
      "status": "todo"
    }
  ],
  "advice": [
    {
      "level": 1,
      "text": "どのコメントが未定義か確認しよう：tri3 と line3 の中身がまだ書かれていない点に気づいてください。"
    },
    {
      "level": 2,
      "text": "tri3 の役割（行をどの順で出すか）と line3 の役割（1行分の '*' を出力しカウント増加）を具体化してみてください。"
    },
    {
      "level": 3,
      "text": "具体的な詳細コメント例：tri3(n): n==0ならreturn; tri3(n-1); line3(n); とし、line3(k): k==0ならreturn; putchar('*')してグローバル（または参照渡し）のカウントを++し line3(k-1) を呼ぶ。 mainでは scanf で n を読み、tri3(n) を呼び、COUNT を計算して printf で表示する。"
    }
  ]
}